<?xml version="1.0" encoding="UTF-8"?><Character Gender="Female" Name="MagePriest" Race="Elf">
  <Attributes DEX="1" HT="-2" IQ="4" NIM="2" SOC="5" STR="-5" TOU="-3"/>
  <Equipment Armor="Chain Mail">
    <Hand Name="right hand">Quarterstaff</Hand>
    <Hand Name="left hand"/>
  </Equipment>
  <Professions>
    <Profession Level="4" Name="Fighter" familiar="" proficient="Quarterstaff"/>
    <Profession Level="2" Name="Athlete" familiar="" proficient="Throwing"/>
    <Profession Level="2" Name="Thief" familiar="" proficient="Stealth"/>
    <Profession Level="3" Name="Spellcasting" familiar="" proficient="Conjuration,Fire"/>
  </Professions>
  <Spells>
    <Spell Familiarity="memorized" Name="Flame Jet"/>
    <Spell Familiarity="memorized" Name="Throw Spell"/>
    <Spell Familiarity="memorized" Name="Control Temperature"/>
    <Spell Familiarity="memorized" Name="Create Fire"/>
  </Spells>
  <Advantages>
    <Advantage LevelName="$200" Name="Wealth"/>
    <Advantage LevelName="5" Name="Divine Aff. - Aphrodite"/>
    <Advantage LevelName="3" Name="Divine Power"/>
    <Advantage LevelName="" Name="Compulsive Liar"/>
    <Advantage LevelName="" Name="Delusional"/>
    <Advantage LevelName="Minor" Name="Phobia"/>
    <Advantage LevelName="x1" Name="Quirks"/>
  </Advantages>
</Character>