<?xml version="1.0"?>
<Character Gender="Male" Name="Sistheen" Race="LizardMan">
  <Attributes DEX="2" HT="3" IQ="-3" NIM="0" SOC="-2" STR="5" TOU="3"/>
  <Equipment Armor="Scale Mail">
    <Hand Name="right hand">Mace</Hand>
    <Hand Name="left hand">Medium Shield</Hand>
    <Belt>Potion:Healing</Belt>
    <Belt>Potion:Minor Healing</Belt>
  </Equipment>
  <Professions>
    <Profession Name="Fighter" Level="6" proficient="Axe/Mace, Shield, Brawling" familiar=""></Profession>
    <Profession Name="Martial Arts" Level="1" proficient="Wrestling" familiar=""></Profession>
  </Professions>
  <Advantages>
    <Advantage Level="7" Name="Wealth"/>
    <Advantage Level="0" Name="Bad Temper"/>
  </Advantages>
</Character>